kmeseg/__init__.py
kmeseg/api/__init__.py
kmeseg/api/tokenize.py
scripts/__init__.py
scripts/process_data.py
scripts/train_model.py
kmeseg-0.1.1.dist-info/METADATA
kmeseg-0.1.1.dist-info/WHEEL
kmeseg-0.1.1.dist-info/top_level.txt
kmeseg-0.1.1.dist-info/RECORD
