Metadata-Version: 2.1
Name: kmeseg
Version: 0.1.1
Summary: Useful AI library for chemistry.
Home-page: https://github.com/namirinz/nami
Author: Nath Prachayakul
Author-email: nath.prachayakul@gmail.com
License: UNKNOWN
Project-URL: Bug Reports, https://github.com/namirinz/nami/issues
Project-URL: Source, https://github.com/namirinz/nami
Keywords: AI,tensorflow,development
Platform: UNKNOWN
Classifier: Development Status :: 4 - Beta
Classifier: Intended Audience :: Developers
Classifier: Topic :: Software Development :: Build Tools
Classifier: License :: OSI Approved :: MIT License
Classifier: Programming Language :: Python :: 3
Classifier: Programming Language :: Python :: 3.5
Classifier: Programming Language :: Python :: 3.6
Classifier: Programming Language :: Python :: 3.7
Classifier: Programming Language :: Python :: 3.8
Classifier: Programming Language :: Python :: 3 :: Only
Requires-Python: >=3.5, <4
Requires-Dist: tensorflow
Requires-Dist: tqdm
